damndeepesh/__init__.py
damndeepesh/cli.py
damndeepesh/data.py
damndeepesh-1.0.0.dist-info/METADATA
damndeepesh-1.0.0.dist-info/WHEEL
damndeepesh-1.0.0.dist-info/entry_points.txt
damndeepesh-1.0.0.dist-info/RECORD
