Metadata-Version: 2.4
Name: damndeepesh
Version: 1.0.0
Summary: Deepesh Gupta's Portfolio in your terminal
Author-email: Deepesh Gupta <hello@deepeshgupta.dev>
Classifier: License :: OSI Approved :: MIT License
Classifier: Operating System :: OS Independent
Classifier: Programming Language :: Python :: 3
Requires-Dist: beautifulsoup4
Requires-Dist: requests
Requires-Dist: rich
